bio_shark/VERSION
bio_shark/__init__.py
bio_shark/exceptions.py
bio_shark/settings.py
bio_shark/capture/__init__.py
bio_shark/capture/capture_utils.py
bio_shark/capture/compute.py
bio_shark/capture/finalize_sharkcapture.py
bio_shark/capture/logic.py
bio_shark/capture/plotting_functions.py
bio_shark/capture/sharkcapture_extended.py
bio_shark/capture/compute_slurm/__init__.py
bio_shark/capture/compute_slurm/gather.py
bio_shark/capture/compute_slurm/prepare.py
bio_shark/capture/compute_slurm/process.py
bio_shark/core/__init__.py
bio_shark/core/alf_scoring.py
bio_shark/core/sequence_pair_similarity.py
bio_shark/core/utils.py
bio_shark/data/SHARKdive_features_boxplot_stats_NGDinvert.pkl
bio_shark/data/dive_pred_model_v2.pkl
bio_shark/data/grantham.tsv
bio_shark/data/sample_fasta_file.fasta
bio_shark/data/substitution_matrix_grantham.tsv
bio_shark/dive/__init__.py
bio_shark/dive/calculate_kmer_scores.py
bio_shark/dive/prediction.py
bio_shark/dive/run.py
bio_shark/dive/visualize.py
bio_shark/dive/visualize_bk.py
bio_shark-2.0.2.dist-info/LICENSE
bio_shark-2.0.2.dist-info/METADATA
bio_shark-2.0.2.dist-info/WHEEL
bio_shark-2.0.2.dist-info/entry_points.txt
bio_shark-2.0.2.dist-info/top_level.txt
bio_shark-2.0.2.dist-info/RECORD
