Metadata-Version: 2.2
Name: bio-shark
Version: 2.0.2
Summary: SHARK (Similarity/Homology Assessment by Relating K-mers)
Home-page: https://git.mpi-cbg.de/tothpetroczylab/shark
Author: Willis Chow <chow@mpi-cbg.de>, Soumyadeep Ghosh <soumyadeep11194@gmail.com>, Anna Hadarovich <hadarovi@mpi-cbg.de>, Agnes Toth-Petroczy <tothpet@mpi-cbg.de>, Maxim Scheremetjew <schereme@mpi-cbg.de>
Author-email: chow@mpi-cbg.de
Project-URL: Homepage, https://git.mpi-cbg.de/tothpetroczylab/shark
Project-URL: Documentation, https://git.mpi-cbg.de/tothpetroczylab/shark/-/blob/master/README.md
Project-URL: Funding, https://www.mpi-cbg.de/
Project-URL: Repository, https://git.mpi-cbg.de/tothpetroczylab/shark
Project-URL: Issue tracker, https://git.mpi-cbg.de/tothpetroczylab/shark/-/issues
Keywords: intrinsically disordered protein regions,motif detection,IDRs,sequence-to-function,alignment-free,machine learning,homology detection
Classifier: Development Status :: 5 - Production/Stable
Classifier: Intended Audience :: Science/Research
Classifier: License :: OSI Approved :: BSD License
Classifier: Topic :: Scientific/Engineering :: Bio-Informatics
Classifier: Programming Language :: Python
Classifier: Programming Language :: Python :: 3
Classifier: Programming Language :: Python :: 3 :: Only
Classifier: Programming Language :: Python :: 3.8
Classifier: Programming Language :: Python :: 3.9
Classifier: Programming Language :: Python :: 3.10
Classifier: Programming Language :: Python :: 3.11
Classifier: Programming Language :: Python :: 3.12
Classifier: Operating System :: Unix
Classifier: Operating System :: MacOS
Requires-Python: >=3.8,<3.13
License-File: LICENSE
Requires-Dist: requests~=2.32.0
Requires-Dist: catboost>=1.0.0
Requires-Dist: matplotlib>=3.5
Requires-Dist: pandas>=1.3
Requires-Dist: logomaker~=0.8
Requires-Dist: alfpy~=1.0.6
Requires-Dist: numpy<2.0.0
Requires-Dist: seaborn==0.13.2
Dynamic: author
Dynamic: author-email
Dynamic: classifier
Dynamic: description
Dynamic: description-content-type
Dynamic: home-page
Dynamic: keywords
Dynamic: project-url
Dynamic: requires-dist
Dynamic: requires-python
Dynamic: summary
